MANIFEST.in
README.md
setup.cfg
setup.py
whoisp/__init__.py
whoisp/parser.py
whoisp.egg-info/PKG-INFO
whoisp.egg-info/SOURCES.txt
whoisp.egg-info/dependency_links.txt
whoisp.egg-info/not-zip-safe
whoisp.egg-info/top_level.txt
whoisp/__pycache__/__init__.cpython-36.pyc
whoisp/__pycache__/parser.cpython-36.pyc