Metadata-Version: 1.1
Name: whoisp
Version: 0.0.2
Summary: simple whois parser
Home-page: https://github.com/amureki/whoisp.git
Author: Rustem Sayargaliev
Author-email: r.sayargaliev@gmail.com
License: MIT
Keywords: domain,whois
Platform: UNKNOWN
Classifier: Development Status :: 3 - Alpha
Classifier: Intended Audience :: Developers
Classifier: License :: OSI Approved :: MIT License
Classifier: Natural Language :: English
Classifier: Programming Language :: Python :: 3
Classifier: Programming Language :: Python :: 3.6
